notia/__init__.py
notia/api.py
notia/apikey.py
notia/config.py
notia/display.py
notia/download_manager.py
notia/errors/__init__.py
notia/login.py
notia/models/__init__.py
notia/models/dataset.py
notia/models/order.py
notia-0.6.1.dist-info/LICENSE
notia-0.6.1.dist-info/WHEEL
notia-0.6.1.dist-info/METADATA
notia-0.6.1.dist-info/RECORD
