Metadata-Version: 2.1
Name: notia
Version: 0.6.1
Summary: A library for interacting with the Notia.ai platform
Home-page: https://notia.ai
Keywords: machine learning,datasets
Author: Notia.ai
Requires-Python: >=3.7.1,<4.0.0
Classifier: Programming Language :: Python :: 3
Classifier: Programming Language :: Python :: 3.10
Classifier: Programming Language :: Python :: 3.8
Classifier: Programming Language :: Python :: 3.9
Requires-Dist: aiohttp (>=3.8.0,<4.0.0)
Requires-Dist: click (>=8.0.3,<9.0.0)
Requires-Dist: ipywidgets (>=7.7.0,<8.0.0)
Requires-Dist: pandas (>=1.3,<2.0)
Requires-Dist: pydantic (>=1.9.0,<2.0.0)
Requires-Dist: requests (>=2.27.1,<3.0.0)
Requires-Dist: rich (>=12.2.0,<13.0.0)
Project-URL: Repository, https://github.com/notia-ai/client
